{"is_source_file": true, "format": "JavaScript", "description": "React component for the 'Add Todo' page, providing a form to create new todo items with title and detail fields.", "external_files": ["../components/StatusBar", "../components/AppBar"], "external_methods": [], "published": ["AddTodoPage"], "classes": [], "methods": [{"name": "AddTodoPage", "description": "React functional component for the add todo page, handles user input for new todo creation."}, {"name": "handleSubmit", "description": "Handles form submission: validates input, invokes onAdd callback, clears form fields."}], "calls": ["React.useState", "alert", "onAdd", "setTitle", "setDetail", "e.preventDefault()", "setTitle('')", "setDetail('')"], "search-terms": ["AddTodoPage", "React", "useState", "form", "todo"], "state": 2, "file_id": 20, "knowledge_revision": 42, "git_revision": "", "ctags": [{"_type": "tag", "name": "AddTodoPage", "path": "/home/kavia/workspace/code-generation/simple-todo-manager-85321-85330/todo_frontend/src/pages/AddTodoPage.js", "pattern": "/^const AddTodoPage = ({ onAdd, onBack }) => {$/", "language": "JavaScript", "kind": "constant"}, {"_type": "tag", "name": "detail", "path": "/home/kavia/workspace/code-generation/simple-todo-manager-85321-85330/todo_frontend/src/pages/AddTodoPage.js", "pattern": "/^            value={detail}$/", "language": "JavaScript", "kind": "field", "scope": "value", "scopeKind": "class"}, {"_type": "tag", "name": "handleSubmit", "path": "/home/kavia/workspace/code-generation/simple-todo-manager-85321-85330/todo_frontend/src/pages/AddTodoPage.js", "pattern": "/^  const handleSubmit = (e) => {$/", "language": "JavaScript", "kind": "constant"}, {"_type": "tag", "name": "onAdd", "path": "/home/kavia/workspace/code-generation/simple-todo-manager-85321-85330/todo_frontend/src/pages/AddTodoPage.js", "pattern": "/^const AddTodoPage = ({ onAdd, onBack }) => {$/", "language": "JavaScript", "kind": "field", "scope": "AddTodoPage", "scopeKind": "class"}, {"_type": "tag", "name": "setDetail", "path": "/home/kavia/workspace/code-generation/simple-todo-manager-85321-85330/todo_frontend/src/pages/AddTodoPage.js", "pattern": "/^  const [detail, setDetail] = useState('');$/", "language": "JavaScript", "kind": "constant"}, {"_type": "tag", "name": "setTitle", "path": "/home/kavia/workspace/code-generation/simple-todo-manager-85321-85330/todo_frontend/src/pages/AddTodoPage.js", "pattern": "/^  const [title, setTitle] = useState('');$/", "language": "JavaScript", "kind": "constant"}, {"_type": "tag", "name": "title", "path": "/home/kavia/workspace/code-generation/simple-todo-manager-85321-85330/todo_frontend/src/pages/AddTodoPage.js", "pattern": "/^            value={title}$/", "language": "JavaScript", "kind": "field", "scope": "value", "scopeKind": "class"}], "hash": "fc235af01ce698ce1a2c77dcab294ceb", "format-version": 4, "code-base-name": "todo_frontend", "filename": "todo_frontend/src/pages/AddTodoPage.js", "fields": [{"name": "value={detail}", "scope": "value", "scopeKind": "class", "description": "unavailable"}, {"name": "const AddTodoPage = ({ onAdd, onBack }) => {", "scope": "AddTodoPage", "scopeKind": "class", "description": "unavailable"}, {"name": "value={title}", "scope": "value", "scopeKind": "class", "description": "unavailable"}], "revision_history": [{"42": ""}]}